scrapydweb/__init__.py
scrapydweb/__version__.py
scrapydweb/common.py
scrapydweb/default_settings.py
scrapydweb/models.py
scrapydweb/run.py
scrapydweb/vars.py
scrapydweb/data/demo_projects/ScrapydWeb_demo/scrapy.cfg
scrapydweb/data/demo_projects/ScrapydWeb_demo/ScrapydWeb_demo/__init__.py
scrapydweb/data/demo_projects/ScrapydWeb_demo/ScrapydWeb_demo/items.py
scrapydweb/data/demo_projects/ScrapydWeb_demo/ScrapydWeb_demo/middlewares.py
scrapydweb/data/demo_projects/ScrapydWeb_demo/ScrapydWeb_demo/pipelines.py
scrapydweb/data/demo_projects/ScrapydWeb_demo/ScrapydWeb_demo/settings.py
scrapydweb/data/demo_projects/ScrapydWeb_demo/ScrapydWeb_demo/spiders/__init__.py
scrapydweb/data/demo_projects/ScrapydWeb_demo/ScrapydWeb_demo/spiders/test.py
scrapydweb/data/parse/ScrapydWeb_demo.log
scrapydweb/static/v152/css/dropdown.css
scrapydweb/static/v152/css/dropdown_mobileui.css
scrapydweb/static/v152/css/icon_upload_icon_right.css
scrapydweb/static/v152/css/multinode.css
scrapydweb/static/v152/css/stacktable.css
scrapydweb/static/v152/css/stats.css
scrapydweb/static/v152/css/style.css
scrapydweb/static/v152/css/style_mobileui.css
scrapydweb/static/v152/css/utf8.css
scrapydweb/static/v152/css/utf8_mobileui.css
scrapydweb/static/v152/element-ui@2.4.6/lib/index.js
scrapydweb/static/v152/element-ui@2.4.6/lib/theme-chalk/index.css
scrapydweb/static/v152/element-ui@2.4.6/lib/theme-chalk/fonts/element-icons.woff
scrapydweb/static/v152/icon/fav.ico
scrapydweb/static/v152/icon/fav.png
scrapydweb/static/v152/icon/spider-man-spiderman-face-mask-round-avatar-512.png
scrapydweb/static/v152/icon/spiderman.png
scrapydweb/static/v152/js/common.js
scrapydweb/static/v152/js/echarts.min.js
scrapydweb/static/v152/js/github_buttons.html
scrapydweb/static/v152/js/github_buttons.js
scrapydweb/static/v152/js/icons_menu.js
scrapydweb/static/v152/js/jquery.min.js
scrapydweb/static/v152/js/multinode.js
scrapydweb/static/v152/js/stacktable.js
scrapydweb/static/v152/js/stats.js
scrapydweb-1.5.2.dist-info/LICENSE
scrapydweb-1.5.2.dist-info/METADATA
scrapydweb-1.5.2.dist-info/WHEEL
scrapydweb-1.5.2.dist-info/entry_points.txt
scrapydweb-1.5.2.dist-info/top_level.txt
scrapydweb-1.5.2.dist-info/RECORD
